{ "columns":10,
 "image":"..\/images\/icons.png",
 "imageheight":64,
 "imagewidth":160,
 "margin":0,
 "name":"icons",
 "spacing":0,
 "tilecount":40,
 "tileheight":16,
 "tileproperties":
    {
     "0":
        {
         "name":"heart"
        },
     "1":
        {
         "name":"bolt"
        },
     "10":
        {
         "name":"gold"
        },
     "11":
        {
         "name":"wood"
        },
     "12":
        {
         "name":"cow"
        },
     "13":
        {
         "name":"crop"
        },
     "14":
        {
         "name":"tree"
        },
     "15":
        {
         "name":"leaf"
        },
     "16":
        {
         "name":"wrench-round"
        },
     "17":
        {
         "name":"tree-small"
        },
     "2":
        {
         "name":"wrench"
        },
     "20":
        {
         "name":"question"
        },
     "21":
        {
         "name":"skull"
        },
     "22":
        {
         "name":"dna"
        },
     "23":
        {
         "name":"mind"
        },
     "24":
        {
         "name":"red-cross-large"
        },
     "25":
        {
         "name":"fish"
        },
     "26":
        {
         "name":"bird"
        },
     "27":
        {
         "name":"red-cross-small"
        },
     "3":
        {
         "name":"up"
        },
     "30":
        {
         "name":"user"
        },
     "31":
        {
         "name":"users1"
        },
     "32":
        {
         "name":"users2"
        },
     "33":
        {
         "name":"plus"
        },
     "34":
        {
         "name":"plant"
        },
     "35":
        {
         "name":"crop1"
        },
     "36":
        {
         "name":"crop2"
        },
     "37":
        {
         "name":"crop3"
        },
     "38":
        {
         "name":"harvest"
        },
     "39":
        {
         "name":"back"
        },
     "4":
        {
         "name":"down"
        },
     "5":
        {
         "name":"left"
        },
     "6":
        {
         "name":"right"
        },
     "7":
        {
         "name":"player-red"
        },
     "8":
        {
         "name":"player-dark"
        }
    },
 "tilepropertytypes":
    {
     "0":
        {
         "name":"string"
        },
     "1":
        {
         "name":"string"
        },
     "10":
        {
         "name":"string"
        },
     "11":
        {
         "name":"string"
        },
     "12":
        {
         "name":"string"
        },
     "13":
        {
         "name":"string"
        },
     "14":
        {
         "name":"string"
        },
     "15":
        {
         "name":"string"
        },
     "16":
        {
         "name":"string"
        },
     "17":
        {
         "name":"string"
        },
     "2":
        {
         "name":"string"
        },
     "20":
        {
         "name":"string"
        },
     "21":
        {
         "name":"string"
        },
     "22":
        {
         "name":"string"
        },
     "23":
        {
         "name":"string"
        },
     "24":
        {
         "name":"string"
        },
     "25":
        {
         "name":"string"
        },
     "26":
        {
         "name":"string"
        },
     "27":
        {
         "name":"string"
        },
     "3":
        {
         "name":"string"
        },
     "30":
        {
         "name":"string"
        },
     "31":
        {
         "name":"string"
        },
     "32":
        {
         "name":"string"
        },
     "33":
        {
         "name":"string"
        },
     "34":
        {
         "name":"string"
        },
     "35":
        {
         "name":"string"
        },
     "36":
        {
         "name":"string"
        },
     "37":
        {
         "name":"string"
        },
     "38":
        {
         "name":"string"
        },
     "39":
        {
         "name":"string"
        },
     "4":
        {
         "name":"string"
        },
     "5":
        {
         "name":"string"
        },
     "6":
        {
         "name":"string"
        },
     "7":
        {
         "name":"string"
        },
     "8":
        {
         "name":"string"
        }
    },
 "tilewidth":16,
 "type":"tileset"
}